appdaemon_testing_fork/__init__.py
appdaemon_testing_fork/hass_driver.py
appdaemon_testing_fork/pytest/__init__.py
appdaemon_testing_fork-0.2.1.dist-info/entry_points.txt
appdaemon_testing_fork-0.2.1.dist-info/WHEEL
appdaemon_testing_fork-0.2.1.dist-info/METADATA
appdaemon_testing_fork-0.2.1.dist-info/RECORD
