Metadata-Version: 2.1
Name: appdaemon-testing-fork
Version: 0.2.1
Summary: 
Home-page: https://github.com/dataisbaye/appdaemon-testing
Author: Brandon Hoeksema
Author-email: brandon.hoeksema@gmail.com
Requires-Python: >=3.9.0
Classifier: Programming Language :: Python :: 3
Classifier: Programming Language :: Python :: 3.9
Classifier: Programming Language :: Python :: 3.10
Project-URL: Repository, https://github.com/dataisbaye/appdaemon-testing
